scikit_build_core/__init__.py
scikit_build_core/_logging.py
scikit_build_core/_shutil.py
scikit_build_core/_version.py
scikit_build_core/_version.pyi
scikit_build_core/cmake.py
scikit_build_core/errors.py
scikit_build_core/format.py
scikit_build_core/program_search.py
scikit_build_core/py.typed
scikit_build_core/_compat/__init__.py
scikit_build_core/_compat/builtins.py
scikit_build_core/_compat/tomllib.py
scikit_build_core/_compat/typing.py
scikit_build_core/_compat/importlib/__init__.py
scikit_build_core/_compat/importlib/metadata.py
scikit_build_core/_compat/importlib/resources.py
scikit_build_core/_vendor/pyproject_metadata/LICENSE
scikit_build_core/_vendor/pyproject_metadata/__init__.py
scikit_build_core/_vendor/pyproject_metadata/constants.py
scikit_build_core/_vendor/pyproject_metadata/errors.py
scikit_build_core/_vendor/pyproject_metadata/project_table.py
scikit_build_core/_vendor/pyproject_metadata/py.typed
scikit_build_core/_vendor/pyproject_metadata/pyproject.py
scikit_build_core/ast/__init__.py
scikit_build_core/ast/ast.py
scikit_build_core/ast/tokenizer.py
scikit_build_core/build/__init__.py
scikit_build_core/build/_editable.py
scikit_build_core/build/_file_processor.py
scikit_build_core/build/_init.py
scikit_build_core/build/_pathutil.py
scikit_build_core/build/_scripts.py
scikit_build_core/build/_wheelfile.py
scikit_build_core/build/generate.py
scikit_build_core/build/metadata.py
scikit_build_core/build/sdist.py
scikit_build_core/build/wheel.py
scikit_build_core/builder/__init__.py
scikit_build_core/builder/__main__.py
scikit_build_core/builder/builder.py
scikit_build_core/builder/generator.py
scikit_build_core/builder/get_requires.py
scikit_build_core/builder/macos.py
scikit_build_core/builder/sysconfig.py
scikit_build_core/builder/wheel_tag.py
scikit_build_core/file_api/__init__.py
scikit_build_core/file_api/_cattrs_converter.py
scikit_build_core/file_api/query.py
scikit_build_core/file_api/reply.py
scikit_build_core/file_api/model/__init__.py
scikit_build_core-0.11.1.dist-info/METADATA
scikit_build_core-0.11.1.dist-info/WHEEL
scikit_build_core-0.11.1.dist-info/entry_points.txt
scikit_build_core-0.11.1.dist-info/licenses/LICENSE
scikit_build_core-0.11.1.dist-info/RECORD
